ants/__init__.py
ants/base_communication.py
ants/base_config.py
ants/base_node.py
ants/heartbeat.py
ants/job.py
ants/message.py
ants/state.py
ants/communications/__init__.py
ants/communications/socketserver.py
pyants-0.2.0.dist-info/LICENSE
pyants-0.2.0.dist-info/METADATA
pyants-0.2.0.dist-info/WHEEL
pyants-0.2.0.dist-info/top_level.txt
pyants-0.2.0.dist-info/RECORD
