Metadata-Version: 2.1
Name: pyants
Version: 0.2.0
Summary: Allow you to create you own custom decentralize job management system.
Home-page: https://github.com/hvuhsg/ants
Author: Yehoyada.s
Author-email: hvuhsg6@gmail.com
License: GPLv3
Keywords: decentralize,job,jobs,job management
Platform: UNKNOWN
Classifier: Development Status :: 3 - Alpha
Classifier: Intended Audience :: Developers
Classifier: License :: OSI Approved :: GNU General Public License v3 (GPLv3)
Classifier: Operating System :: OS Independent
Classifier: Natural Language :: English
Classifier: Programming Language :: Python :: 3
Classifier: Programming Language :: Python :: 3.6
Classifier: Programming Language :: Python :: 3.7
Classifier: Programming Language :: Python :: 3.8
Classifier: Programming Language :: Python :: 3.9
Classifier: Programming Language :: Python :: 3.10
License-File: LICENSE
